{"1577636077514":[{"title":"Vue2.5开发去哪儿网App","count":11},{"title":"React 16.4 开发简书项目","count":41},{"title":"React服务器渲染原理解析与实践","count":12},{"title":"手把手带你掌握新版Webpack4.0","count":85}],"1577636592798":[{"title":"Vue2.5开发去哪儿网App","count":89},{"title":"React 16.4 开发简书项目","count":78},{"title":"React服务器渲染原理解析与实践","count":64},{"title":"手把手带你掌握新版Webpack4.0","count":27}],"1577724382456":[{"title":"Vue2.5开发去哪儿网App","count":33},{"title":"React 16.4 开发简书项目","count":56},{"title":"React服务器渲染原理解析与实践","count":38},{"title":"手把手带你掌握新版Webpack4.0","count":99}],"1593325738916":[{"title":"Vue2.5开发去哪儿网App 从零基础入门到实战项目","count":null},{"title":"React 16.4 开发简书项目 从零基础入门到实战","count":null},{"title":"Vue2.5开发去哪儿网App 从零基础入门到实战项目","count":null},{"title":"从基础到实战\t手把手带你掌握新版Webpack4.0","count":null},{"title":"Dell Lee 的微课堂，职业规划答疑解惑，精彩文章与你分享","count":null}],"1593506180057":[{"title":"Vue2.5开发去哪儿网App 从零基础入门到实战项目","count":null},{"title":"React 16.4 开发简书项目 从零基础入门到实战","count":null},{"title":"Vue2.5开发去哪儿网App 从零基础入门到实战项目","count":null},{"title":"从基础到实战\t手把手带你掌握新版Webpack4.0","count":null},{"title":"Dell Lee 的微课堂，职业规划答疑解惑，精彩文章与你分享","count":null}]}